plutous/__init__.py
plutous/__main__.py
plutous/app/__init__.py
plutous/app/main.py
plutous/app/utils/__init__.py
plutous/app/utils/session.py
plutous/cli/__init__.py
plutous/cli/main.py
plutous/cli/utils.py
plutous/config.py
plutous/database.py
plutous/enums/__init__.py
plutous/enums/exchange.py
plutous/models/__init__.py
plutous/models/base.py
plutous-0.0.30.dist-info/LICENSE
plutous-0.0.30.dist-info/METADATA
plutous-0.0.30.dist-info/WHEEL
plutous-0.0.30.dist-info/entry_points.txt
plutous-0.0.30.dist-info/RECORD
