Metadata-Version: 2.1
Name: plutous
Version: 0.0.30
Summary: Plutous Library
License: MIT
Author: Cheun Hong
Author-email: cheunhong@plutous.io
Requires-Python: >=3.11,<3.12
Classifier: Intended Audience :: Developers
Classifier: License :: OSI Approved :: MIT License
Classifier: Operating System :: OS Independent
Classifier: Programming Language :: Python :: 3
Classifier: Programming Language :: Python :: 3.11
Requires-Dist: PyYAML (>=6.0)
Requires-Dist: SQLAlchemy (>=2.0.12)
Requires-Dist: alembic (>=1.10.4)
Requires-Dist: fastapi (>=0.95.1)
Requires-Dist: loguru (>=0.6.0)
Requires-Dist: psycopg2 (>=2.9.6)
Requires-Dist: pydantic (>=1.10.7)
Requires-Dist: sentry-sdk (>=1.25.0)
Requires-Dist: sqlalchemy_utils (>=0.41.1)
Requires-Dist: typer (>=0.9.0)
Requires-Dist: uvicorn (>=0.22.0)
